mlarchive2maildir/__init__.py
mlarchive2maildir/commands.py
mlarchive2maildir/mailbox.py
mlarchive2maildir/message.py
mlarchive2maildir/pipermail.py
mlarchive2maildir-0.0.1.dist-info/DESCRIPTION.rst
mlarchive2maildir-0.0.1.dist-info/METADATA
mlarchive2maildir-0.0.1.dist-info/RECORD
mlarchive2maildir-0.0.1.dist-info/WHEEL
mlarchive2maildir-0.0.1.dist-info/entry_points.txt
mlarchive2maildir-0.0.1.dist-info/metadata.json
mlarchive2maildir-0.0.1.dist-info/top_level.txt
