Metadata-Version: 2.0
Name: mlarchive2maildir
Version: 0.0.1
Summary: Imports mail from (pipermail) archives into a maildir
Home-page: UNKNOWN
Author: Florian Klink
Author-email: flokli@flokli.de
License: MIT
Platform: UNKNOWN
Requires-Dist: bs4
Requires-Dist: cleo
Requires-Dist: requests
